autoeft/__init__.py
autoeft/cli.py
autoeft/exceptions.py
autoeft/utils.py
autoeft/base/__init__.py
autoeft/base/basis.py
autoeft/base/classifications.py
autoeft/base/groups.py
autoeft/base/model.py
autoeft/base/representations.py
autoeft/base/tensors.py
autoeft/combinatorics/__init__.py
autoeft/combinatorics/generators.py
autoeft/combinatorics/symmetric_group.py
autoeft/combinatorics/young.py
autoeft/combinatorics/gens/__init__.py
autoeft/combinatorics/gens/S_2/P_1_1_cycle.npz
autoeft/combinatorics/gens/S_2/P_1_1_reflection.npz
autoeft/combinatorics/gens/S_2/P_2_cycle.npz
autoeft/combinatorics/gens/S_2/P_2_reflection.npz
autoeft/combinatorics/gens/S_2/__init__.py
autoeft/combinatorics/gens/S_3/P_1_1_1_cycle.npz
autoeft/combinatorics/gens/S_3/P_1_1_1_reflection.npz
autoeft/combinatorics/gens/S_3/P_2_1_cycle.npz
autoeft/combinatorics/gens/S_3/P_2_1_reflection.npz
autoeft/combinatorics/gens/S_3/P_3_cycle.npz
autoeft/combinatorics/gens/S_3/P_3_reflection.npz
autoeft/combinatorics/gens/S_3/__init__.py
autoeft/combinatorics/gens/S_4/P_1_1_1_1_cycle.npz
autoeft/combinatorics/gens/S_4/P_1_1_1_1_reflection.npz
autoeft/combinatorics/gens/S_4/P_2_1_1_cycle.npz
autoeft/combinatorics/gens/S_4/P_2_1_1_reflection.npz
autoeft/combinatorics/gens/S_4/P_2_2_cycle.npz
autoeft/combinatorics/gens/S_4/P_2_2_reflection.npz
autoeft/combinatorics/gens/S_4/P_3_1_cycle.npz
autoeft/combinatorics/gens/S_4/P_3_1_reflection.npz
autoeft/combinatorics/gens/S_4/P_4_cycle.npz
autoeft/combinatorics/gens/S_4/P_4_reflection.npz
autoeft/combinatorics/gens/S_4/__init__.py
autoeft/combinatorics/gens/S_5/P_1_1_1_1_1_cycle.npz
autoeft/combinatorics/gens/S_5/P_1_1_1_1_1_reflection.npz
autoeft/combinatorics/gens/S_5/P_2_1_1_1_cycle.npz
autoeft/combinatorics/gens/S_5/P_2_1_1_1_reflection.npz
autoeft/combinatorics/gens/S_5/P_2_2_1_cycle.npz
autoeft/combinatorics/gens/S_5/P_2_2_1_reflection.npz
autoeft/combinatorics/gens/S_5/P_3_1_1_cycle.npz
autoeft/combinatorics/gens/S_5/P_3_1_1_reflection.npz
autoeft-1.0.1.dist-info/METADATA
autoeft-1.0.1.dist-info/WHEEL
autoeft-1.0.1.dist-info/entry_points.txt
autoeft-1.0.1.dist-info/licenses/LICENSE
autoeft-1.0.1.dist-info/RECORD
