Metadata-Version: 2.1
Name: autoeft
Version: 1.0.1
Summary: Automated operator construction for effective field theories.
Project-URL: Homepage, https://gitlab.com/auto_eft/autoeft
Author-email: "Robert V. Harlander" <harlander@physik.rwth-aachen.de>, "Magnus C. Schaaf" <magnus.schaaf@rwth-aachen.de>
Maintainer-email: "Magnus C. Schaaf" <magnus.schaaf@rwth-aachen.de>
License: MIT License
License-File: LICENSE
Keywords: basis,eft,hep,operators,physics,qft
Classifier: Development Status :: 5 - Production/Stable
Classifier: Environment :: Console
Classifier: Intended Audience :: Science/Research
Classifier: License :: OSI Approved :: MIT License
Classifier: Operating System :: Unix
Classifier: Programming Language :: Python
Classifier: Programming Language :: Python :: 3
Classifier: Programming Language :: Python :: 3.8
Classifier: Programming Language :: Python :: 3.9
Classifier: Programming Language :: Python :: 3.10
Classifier: Programming Language :: Python :: 3.11
Classifier: Topic :: Scientific/Engineering :: Physics
Requires-Python: >=3.8
Requires-Dist: numpy>=1.18
Requires-Dist: packaging>=17.1
Requires-Dist: pydantic~=1.9
Requires-Dist: pyyaml>=5.2
Requires-Dist: rich>=12.3
Requires-Dist: scipy>=1.8
Requires-Dist: semver>=3.0
